wyqpython/__init__.py
wyqpython/base/__init__.py
wyqpython/base/_path.py
wyqpython/base/path.py
wyqpython/io/__init__.py
wyqpython/io/_directory.py
wyqpython/io/_file.py
wyqpython/io/directory.py
wyqpython/io/file.py
wyqpython-0.1.5.dist-info/DESCRIPTION.rst
wyqpython-0.1.5.dist-info/METADATA
wyqpython-0.1.5.dist-info/RECORD
wyqpython-0.1.5.dist-info/WHEEL
wyqpython-0.1.5.dist-info/metadata.json
wyqpython-0.1.5.dist-info/top_level.txt
