Metadata-Version: 2.0
Name: wyqpython
Version: 0.1.5
Summary: The WYQ Python Functions
Home-page: http://www.gamescome.com
Author: WYQ
Author-email: 194897868@qq.com
License: GPL
Download-URL: http://www.gamescome.com
Keywords: tool utils lib
Platform: UNKNOWN
